ocr_general_method/__init__.py
ocr_general_method/coordinate.py
ocr_general_method/exception_utils.py
ocr_general_method/file_utils.py
ocr_general_method/http_utils.py
ocr_general_method/mongo_utils.py
ocr_general_method/other_utils.py
ocr_general_method-0.0.16.dist-info/LICENSE
ocr_general_method-0.0.16.dist-info/METADATA
ocr_general_method-0.0.16.dist-info/WHEEL
ocr_general_method-0.0.16.dist-info/top_level.txt
ocr_general_method-0.0.16.dist-info/RECORD
