Metadata-Version: 2.1
Name: ocr-general-method
Version: 0.0.16
Summary: test PyPI
Author-email: Example Author <author@example.com>
Classifier: Programming Language :: Python :: 3
Classifier: License :: OSI Approved :: MIT License
Classifier: Operating System :: OS Independent
Requires-Python: >=3.7
License-File: LICENSE
